.gitignore
README.rst
rdopts.py
setup.py
rdopts.egg-info/PKG-INFO
rdopts.egg-info/SOURCES.txt
rdopts.egg-info/dependency_links.txt
rdopts.egg-info/entry_points.txt
rdopts.egg-info/top_level.txt