Metadata-Version: 1.0
Name: rdopts
Version: 0.1.3
Summary: A custom setuptools command for reading from setup.cfg
Home-page: UNKNOWN
Author: UNKNOWN
Author-email: UNKNOWN
License: UNKNOWN
Platform: UNKNOWN
